lib/__init__.py
lib/bitbucket.py
lib/git.py
lib/github.py
lib/http.py
lib/logging.py
lib/sourcerio.py
lib/utils.py
sourcerio-0.3.2.data/scripts/sourcerio
sourcerio-0.3.2.dist-info/METADATA
sourcerio-0.3.2.dist-info/WHEEL
sourcerio-0.3.2.dist-info/top_level.txt
sourcerio-0.3.2.dist-info/RECORD
