Metadata-Version: 2.1
Name: sourcerio
Version: 0.3.2
Summary: Backup tool for Bitbucket Cloud and Github
Home-page: https://github.com/Devolutions/sourcerio
Author: Jean-Francois Theroux
Author-email: jftheroux@devolutions.net
License: MIT
Keywords: backup,bitbucket,github
Platform: any
Classifier: Programming Language :: Python :: 3
Classifier: License :: OSI Approved :: MIT License
Classifier: Operating System :: OS Independent
Requires-Dist: pygithub
Requires-Dist: requests
